README.md
setup.cfg
setup.py
cool_functions/__init__.py
cool_functions/cool_functions.py
cool_functions.egg-info/PKG-INFO
cool_functions.egg-info/SOURCES.txt
cool_functions.egg-info/dependency_links.txt
cool_functions.egg-info/not-zip-safe
cool_functions.egg-info/top_level.txt