Metadata-Version: 1.0
Name: cool-functions
Version: 0.1
Summary: Some Useful Functions
Home-page: UNKNOWN
Author: UNKNOWN
Author-email: UNKNOWN
License: UNKNOWN
Platform: UNKNOWN
